helplotlib/__init__.py
helplotlib/helplotlib.py
helplotlib-0.0.1.dist-info/AUTHORS.rst
helplotlib-0.0.1.dist-info/LICENSE
helplotlib-0.0.1.dist-info/METADATA
helplotlib-0.0.1.dist-info/WHEEL
helplotlib-0.0.1.dist-info/top_level.txt
helplotlib-0.0.1.dist-info/RECORD
