Metadata-Version: 2.1
Name: helplotlib
Version: 0.0.1
Summary: Helper for matplotlib: tired of googling over and over again how to change my font size or make my axis semi-log, I am creating this helper to automate all of this. Use it if you want to.
Home-page: https://github.com/bgailleton/helplotlib
Author: Boris Gailleton
Author-email: boris.gailleton@gfz-potsdam.de
License: MIT license
Keywords: helplotlib
Platform: UNKNOWN
Classifier: Development Status :: 2 - Pre-Alpha
Classifier: Intended Audience :: Developers
Classifier: License :: OSI Approved :: MIT License
Classifier: Natural Language :: English
Classifier: Programming Language :: Python :: 3
Classifier: Programming Language :: Python :: 3.5
Classifier: Programming Language :: Python :: 3.6
Classifier: Programming Language :: Python :: 3.7
Classifier: Programming Language :: Python :: 3.8
Requires-Python: >=3.5
Requires-Dist: matplotlib
